dnv/__init__.py
dnv/infidep_helpers/__init__.py
dnv/infidep_helpers/example.py
dnv/infidep_helpers/infidep_helpers.py
dnv_infidep_helpers-0.1.3.dist-info/LICENSE
dnv_infidep_helpers-0.1.3.dist-info/METADATA
dnv_infidep_helpers-0.1.3.dist-info/WHEEL
dnv_infidep_helpers-0.1.3.dist-info/top_level.txt
dnv_infidep_helpers-0.1.3.dist-info/RECORD
